legiond/__init__.py
legiond/cli.py
legiond/config.py
legiond-0.2.4.dist-info/entry_points.txt
legiond-0.2.4.dist-info/LICENSE
legiond-0.2.4.dist-info/WHEEL
legiond-0.2.4.dist-info/METADATA
legiond-0.2.4.dist-info/RECORD
