Metadata-Version: 2.1
Name: legiond
Version: 0.2.4
Summary: A distributed, scalable, and fault-tolerant alerting and monitoring system
Home-page: https://gitlab.com/legion-robotnik/legiond
License: GPL-3.0-only
Author: Eugene Kovalev
Author-email: eugene@kovalev.systems
Requires-Python: >=3.8,<4.0
Classifier: Development Status :: 3 - Alpha
Classifier: Intended Audience :: Developers
Classifier: License :: OSI Approved :: GNU General Public License v3 (GPLv3)
Classifier: Operating System :: OS Independent
Classifier: Programming Language :: Python
Classifier: Programming Language :: Python :: 3
Classifier: Programming Language :: Python :: 3.10
Classifier: Programming Language :: Python :: 3.8
Classifier: Programming Language :: Python :: 3.9
Requires-Dist: click (>=8.0.3,<9.0.0)
Requires-Dist: legion-utils (>=0.2.10,<0.3.0)
Requires-Dist: robotnikmq (>=0.3.3,<0.4.0)
Project-URL: Documentation, https://gitlab.com/legion-robotnik/legiond/-/wikis/home
Project-URL: Repository, https://gitlab.com/legion-robotnik/legiond
